super_scad_smooth_profiles/Chamfer.py
super_scad_smooth_profiles/ExteriorChamferWidget.py
super_scad_smooth_profiles/ExteriorFilletWidget.py
super_scad_smooth_profiles/Fillet.py
super_scad_smooth_profiles/InteriorChamferWidget.py
super_scad_smooth_profiles/InteriorFilletWidget.py
super_scad_smooth_profiles/Lollipop.py
super_scad_smooth_profiles/__init__.py
super_scad_smooth_profiles-0.6.4.dist-info/LICENSE
super_scad_smooth_profiles-0.6.4.dist-info/METADATA
super_scad_smooth_profiles-0.6.4.dist-info/WHEEL
super_scad_smooth_profiles-0.6.4.dist-info/RECORD
