Metadata-Version: 2.3
Name: Super-SCAD-Smooth-Profiles
Version: 0.6.4
Summary: Implementation of smooth profiles.
License: MIT
Keywords: OpenSCAD,SuperSCAD,Smooth Profile
Author: P.R. Water
Author-email: p.r.water@setbased.nl
Requires-Python: >=3.13,<4.0
Classifier: Development Status :: 5 - Production/Stable
Classifier: Intended Audience :: Developers
Classifier: Intended Audience :: Manufacturing
Classifier: License :: OSI Approved :: MIT License
Classifier: Programming Language :: Python :: 3
Classifier: Programming Language :: Python :: 3.13
Classifier: Programming Language :: Python :: 3.11
Classifier: Programming Language :: Python :: 3.12
Classifier: Topic :: Multimedia :: Graphics :: 3D Modeling
Classifier: Topic :: Software Development :: Code Generators
Requires-Dist: super-scad (>=0.11.0,<0.12.0)
Requires-Dist: super-scad-circle-plus (>=0.9.10,<0.10.0)
Requires-Dist: super-scad-smooth-profile (>=0.6.3,<0.7.0)
Project-URL: Documentation, https://superscad.readthedocs.io/
Project-URL: Repository, https://github.com/SuperSCAD/SmoothProfiles
